hlmagix/__init__.py
hlmagix/hlcalculator/__init__.py
hlmagix/hlcalculator/__main__.py
hlmagix/hlcalculator/calculator.py
hlmagix/hlcalculator/cli.py
hlmagix/hlcalculator/parser.py
hlmagix/models/__init__.py
hlmagix/models/product.py
hlmagix/models/user.py
hlmagix/utils/__init__.py
hlmagix/utils/math_utils.py
hlmagix/utils/string_utils.py
hlmagix-0.4.2.dist-info/METADATA
hlmagix-0.4.2.dist-info/WHEEL
hlmagix-0.4.2.dist-info/entry_points.txt
hlmagix-0.4.2.dist-info/RECORD
