Metadata-Version: 2.3
Name: hlmagix
Version: 0.4.2
Summary: HLMagix toolset including calculator, models and utilities
License: MIT
Author: yangfan_hailv
Author-email: fan.yang@elestyle.jp
Requires-Python: >=3.12,<4.0
Classifier: License :: OSI Approved :: MIT License
Classifier: Programming Language :: Python :: 3
Classifier: Programming Language :: Python :: 3.12
Classifier: Programming Language :: Python :: 3.13
Project-URL: Repository, https://github.com/hailv/hlmagix
